validmind/__init__.py
validmind/__version__.py
validmind/ai/test_descriptions.py
validmind/ai/utils.py
validmind/api_client.py
validmind/client.py
validmind/client_config.py
validmind/datasets/__init__.py
validmind/datasets/classification/__init__.py
validmind/datasets/classification/customer_churn.py
validmind/datasets/classification/datasets/bank_customer_churn.csv
validmind/datasets/classification/datasets/taiwan_credit.csv
validmind/datasets/classification/taiwan_credit.py
validmind/datasets/cluster/digits.py
validmind/datasets/credit_risk/__init__.py
validmind/datasets/credit_risk/datasets/lending_club_biased.csv.gz
validmind/datasets/credit_risk/datasets/lending_club_loan_data_2007_2014_clean.csv.gz
validmind/datasets/credit_risk/lending_club.py
validmind/datasets/credit_risk/lending_club_bias.py
validmind/datasets/llm/__init__.py
validmind/datasets/llm/agent_dataset.py
validmind/datasets/llm/rag/__init__.py
validmind/datasets/llm/rag/datasets/rfp_existing_questions_client_1.csv
validmind/datasets/llm/rag/datasets/rfp_existing_questions_client_2.csv
validmind/datasets/llm/rag/datasets/rfp_existing_questions_client_3.csv
validmind/datasets/llm/rag/datasets/rfp_existing_questions_client_4.csv
validmind/datasets/llm/rag/datasets/rfp_existing_questions_client_5.csv
validmind/datasets/llm/rag/rfp.py
validmind/datasets/nlp/__init__.py
validmind/datasets/nlp/cnn_dailymail.py
validmind/datasets/nlp/datasets/Covid_19.csv
validmind/datasets/nlp/datasets/cnn_dailymail_100_with_predictions.csv
validmind/datasets/nlp/datasets/cnn_dailymail_500_with_predictions.csv
validmind/datasets/nlp/datasets/sentiments_with_predictions.csv
validmind/datasets/nlp/twitter_covid_19.py
validmind/datasets/regression/__init__.py
validmind/datasets/regression/california_housing.py
validmind/datasets/regression/datasets/fred/CPIAUCSL.csv
validmind/datasets/regression/datasets/fred/CSUSHPISA.csv
validmind/datasets/regression/datasets/fred/DRSFRMACBS.csv
validmind-2.11.0.dist-info/METADATA
validmind-2.11.0.dist-info/WHEEL
validmind-2.11.0.dist-info/entry_points.txt
validmind-2.11.0.dist-info/licenses/LICENSE
validmind-2.11.0.dist-info/RECORD
