Metadata-Version: 2.4
Name: validmind
Version: 2.11.0
Summary: ValidMind Library
License: DUAL LICENSE NOTICE
License-File: LICENSE
Author: Andres Rodriguez
Author-email: andres@validmind.ai
Requires-Python: >=3.9,<3.13
Classifier: License :: Other/Proprietary License
Classifier: Programming Language :: Python :: 3
Classifier: Programming Language :: Python :: 3.9
Classifier: Programming Language :: Python :: 3.10
Classifier: Programming Language :: Python :: 3.11
Classifier: Programming Language :: Python :: 3.12
Provides-Extra: all
Provides-Extra: credit-risk
Provides-Extra: datasets
Provides-Extra: explainability
Provides-Extra: huggingface
Provides-Extra: llm
Provides-Extra: nlp
Provides-Extra: pii-detection
Provides-Extra: pytorch
Provides-Extra: stats
Provides-Extra: xgboost
Requires-Dist: aiohttp[speedups]
Requires-Dist: anywidget
Requires-Dist: arch ; extra == "all"
Requires-Dist: arch ; extra == "stats"
Requires-Dist: beautifulsoup4
Requires-Dist: bert-score (>=0.3.13) ; extra == "all"
Requires-Dist: bert-score (>=0.3.13) ; extra == "nlp"
Requires-Dist: datasets (>=2.10.0,<3.0.0) ; extra == "datasets"
Requires-Dist: deepeval (>3.3.9) ; extra == "llm"
Requires-Dist: evaluate ; extra == "all"
Requires-Dist: evaluate ; extra == "nlp"
Requires-Dist: ipywidgets
Requires-Dist: kaleido (>=0.2.1,!=0.2.1.post1,<1.0.0)
Requires-Dist: langchain-openai (>=0.1.8) ; extra == "all"
Requires-Dist: langchain-openai (>=0.1.8) ; extra == "llm"
Requires-Dist: langdetect ; extra == "all"
Requires-Dist: langdetect ; extra == "nlp"
Requires-Dist: matplotlib
Requires-Dist: mistune (>=3.0.2,<4.0.0)
Requires-Dist: nest-asyncio (>=1.6.0,<2.0.0)
Requires-Dist: nltk (>=3.8.1,<4.0.0) ; extra == "all"
Requires-Dist: nltk (>=3.8.1,<4.0.0) ; extra == "nlp"
Requires-Dist: numpy (>=1.23,<2.0.0)
Requires-Dist: openai (>=1)
Requires-Dist: pandas (>=2.0.3,<3.0.0)
Requires-Dist: plotly (>=5.0.0,<6.0.0)
Requires-Dist: polars
Requires-Dist: presidio-analyzer ; extra == "pii-detection"
Requires-Dist: presidio-structured ; extra == "pii-detection"
Requires-Dist: pyarrow (<16) ; extra == "nlp"
Requires-Dist: pycocoevalcap ; extra == "all"
Requires-Dist: pycocoevalcap ; extra == "llm"
Requires-Dist: python-dotenv
Requires-Dist: ragas (>=0.2.3,<=0.2.7) ; extra == "all"
Requires-Dist: ragas (>=0.2.3,<=0.2.7) ; extra == "llm"
Requires-Dist: rouge (>=1) ; extra == "all"
Requires-Dist: rouge (>=1) ; extra == "nlp"
Requires-Dist: scikit-learn
Requires-Dist: scipy ; extra == "all"
Requires-Dist: scipy ; extra == "stats"
Requires-Dist: scorecardpy (>=0.1.9.6,<0.2.0) ; extra == "all"
Requires-Dist: scorecardpy (>=0.1.9.6,<0.2.0) ; extra == "credit-risk"
Requires-Dist: seaborn
Requires-Dist: sentencepiece (>=0.2.0,<0.3.0) ; extra == "all"
Requires-Dist: sentencepiece (>=0.2.0,<0.3.0) ; extra == "huggingface"
Requires-Dist: sentencepiece (>=0.2.0,<0.3.0) ; extra == "llm"
Requires-Dist: shap (>=0.46.0) ; extra == "all"
Requires-Dist: shap (>=0.46.0) ; extra == "explainability"
Requires-Dist: statsmodels ; extra == "all"
Requires-Dist: statsmodels ; extra == "stats"
Requires-Dist: tabulate (>=0.9.0,<0.10.0)
Requires-Dist: textblob (>=0.18.0.post0,<0.19.0) ; extra == "all"
Requires-Dist: textblob (>=0.18.0.post0,<0.19.0) ; extra == "nlp"
Requires-Dist: tiktoken
Requires-Dist: torch (>=2.0.0) ; extra == "all"
Requires-Dist: torch (>=2.0.0) ; extra == "llm"
Requires-Dist: torch (>=2.0.0) ; extra == "pytorch"
Requires-Dist: tqdm
Requires-Dist: transformers (>=4.32.0,<5.0.0) ; extra == "all"
Requires-Dist: transformers (>=4.32.0,<5.0.0) ; extra == "huggingface"
Requires-Dist: transformers (>=4.32.0,<5.0.0) ; extra == "llm"
Requires-Dist: xgboost (>=1.5.2,<3) ; extra == "all"
Requires-Dist: xgboost (>=1.5.2,<3) ; extra == "xgboost"
